ads1015/__init__.py
ads1015-0.0.8.dist-info/LICENSE.txt
ads1015-0.0.8.dist-info/METADATA
ads1015-0.0.8.dist-info/WHEEL
ads1015-0.0.8.dist-info/top_level.txt
ads1015-0.0.8.dist-info/RECORD
